__init__.py
analyzer.py
gke.py
gsa.py
reporter.py
wi_analyzer-0.1.3.dist-info/LICENSE.md
wi_analyzer-0.1.3.dist-info/METADATA
wi_analyzer-0.1.3.dist-info/WHEEL
wi_analyzer-0.1.3.dist-info/entry_points.txt
wi_analyzer-0.1.3.dist-info/top_level.txt
wi_analyzer-0.1.3.dist-info/RECORD
