Metadata-Version: 2.1
Name: wi-analyzer
Version: 0.1.3
Summary: GKE Workload Identity Analyzer
Author-email: Eyal Zekaria <eyal.z@doit-intl.com>
Keywords: gke,workload-identity
Classifier: Programming Language :: Python :: 3 :: Only
Requires-Python: >=3.7
License-File: LICENSE.md
Requires-Dist: google-api-python-client (==2.58.0)
Requires-Dist: kubernetes (==24.2.0)
